{
  "ColorGlobalPrimary100": "#007db3",
  "ColorGlobalPrimary000": "#ffffff",
  "ColorGlobalSecondary100": "#454d56",
  "ColorGlobalSecondary90": "#5b6772",
  "ColorGlobalAccent100": "#18cee7",
  "ColorGlobalAccent70": "#8ce7f3",
  "ColorGlobalAccent110": "#13a5b9",
  "ColorGlobalAccent120": "#0f7d8a",
  "ColorGlobalDarkPrimary110": "#005980",
  "ColorGlobalDarkPrimary115": "#004766",
  "ColorGlobalDarkPrimary120": "#00354c",
  "ColorGlobalDarkPrimary130": "#00121a",
  "ColorGlobalMidPrimary70": "#82b4c9",
  "ColorGlobalMidPrimary80": "#47a8d1",
  "ColorGlobalMidPrimary90": "#1798cf",
  "ColorGlobalLightPrimary40": "#edf4f7",
  "ColorGlobalLightPrimary50": "#c2e2f0",
  "ColorGlobalLightPrimary60": "#8cd4f2",
  "ColorGlobalDarkSecondary130": "#000000",
  "ColorGlobalDarkSecondary125": "#0b0d0e",
  "ColorGlobalDarkSecondary120": "#17191c",
  "ColorGlobalDarkSecondary110": "#2d3339",
  "ColorGlobalMidSecondary90": "#5b6571",
  "ColorGlobalMidSecondary80": "#727f8d",
  "ColorGlobalMidSecondary70": "#8e98a4",
  "ColorGlobalLightSecondary60": "#aab2bb",
  "ColorGlobalLightSecondary50": "#c6ccd2",
  "ColorGlobalLightSecondary40": "#e3e5e8",
  "ColorGlobalSemanticSuccesso100": "#049894",
  "ColorGlobalSemanticAlert100": "#aa224f",
  "ColorGlobalSemanticWarning100": "#e26334",
  "ColorGlobalSemanticInfo100": "#0077a3",
  "ColorGlobalSemanticAlert110": "#7f1a3b",
  "ColorGlobalSemanticAlert120": "#551128",
  "ColorGlobalSemanticAlert130": "#3f0d1b",
  "ColorGlobalGradient01": "#000000",
  "ColorGlobalGradient02": "#000000",
  "ColorAliasInteractiveAccentDefault": "#18cee7",
  "ColorAliasInteractiveAccentHover": "#8ce7f3",
  "ColorAliasInteractiveAccentFocus": "#13a5b9",
  "ColorAliasInteractiveAccentPressed": "#0f7d8a",
  "ColorAliasInteractivePrimaryDefault": "#007db3",
  "ColorAliasInteractivePrimaryHover": "#005980",
  "ColorAliasInteractivePrimaryFocus": "#004766",
  "ColorAliasInteractivePrimaryPressed": "#00354c",
  "ColorAliasInteractiveSecondaryDefault": "#454d56",
  "ColorAliasInteractiveSecondaryHover": "#2d3339",
  "ColorAliasInteractiveSecondaryFocus": "#17191c",
  "ColorAliasInteractiveSecondaryPressed": "#0b0d0e",
  "ColorAliasInteractiveRedDefault": "#aa224f",
  "ColorAliasInteractiveRedHover": "#7f1a3b",
  "ColorAliasInteractiveRedFocus": "#551128",
  "ColorAliasInteractiveRedPressed": "#3f0d1b",
  "ColorAliasTextColorDisabled": "#8e98a4",
  "ColorAliasTextColorPrimaryLight0": "#ffffff",
  "ColorAliasTextColorPrimaryLight1": "#edf4f7",
  "ColorAliasTextColorSecondaryDark1": "#454d56",
  "ColorAliasTextColorSecondaryDark0": "#000000",
  "ColorAliasTextColorPrimaryDark0": "#005980",
  "ColorAliasBackgroundColorDisabled": "#c6ccd2",
  "ColorAliasBackgroundColorPrimaryLight1": "#edf4f7",
  "ColorAliasBackgroundColorPrimaryLight0": "#ffffff",
  "ColorAliasBackgroundColorPrimaryDark0": "#00354c",
  "ColorAliasInteractiveBorderFocus": "#454d56",
  "ColorAliasGradientAccentPrimaryDark": "#000000",
  "ColorAliasGradientAccentPrimary": "#000000",
  "data-entry-label-color-default": {"value":"#454d56","type":"color","description":"🟣 Token alias: Colore declinato dal secondario che identifica un elemento con cui l’utente può interagire","filePath":"tokens/design-tokens-example.json","isSource":true,"original":{"value":"{color.global.secondary-100.value}","type":"color","description":"🟣 Token alias: Colore declinato dal secondario che identifica un elemento con cui l’utente può interagire"},"name":"interactive-secondary-default","attributes":{},"path":["color","alias","interactive-secondary-default"]},
  "data-entry-label-color-hover": {"value":"#005980","type":"color","description":"🟣 Token alias: Colore declinato dal primario che identifica il passaggio del mouse su un elemento","filePath":"tokens/design-tokens-example.json","isSource":true,"original":{"value":"{color.global.dark-primary-110.value}","type":"color","description":"🟣 Token alias: Colore declinato dal primario che identifica il passaggio del mouse su un elemento"},"name":"interactive-primary-hover","attributes":{},"path":["color","alias","interactive-primary-hover"]},
  "data-entry-label-color-focus": {"value":"#004766","type":"color","description":"🟣 Token alias: Colore declinato dal primario che identifica la selezione di un elemento usando una tastiera o una voce","filePath":"tokens/design-tokens-example.json","isSource":true,"original":{"value":"{color.global.dark-primary-115.value}","type":"color","description":"🟣 Token alias: Colore declinato dal primario che identifica la selezione di un elemento usando una tastiera o una voce"},"name":"interactive-primary-focus","attributes":{},"path":["color","alias","interactive-primary-focus"]},
  "data-entry-label-color-valued": {"value":"#454d56","type":"color","description":"🟣 Token alias: Colore declinato dal secondario che identifica un elemento con cui l’utente può interagire","filePath":"tokens/design-tokens-example.json","isSource":true,"original":{"value":"{color.global.secondary-100.value}","type":"color","description":"🟣 Token alias: Colore declinato dal secondario che identifica un elemento con cui l’utente può interagire"},"name":"interactive-secondary-default","attributes":{},"path":["color","alias","interactive-secondary-default"]},
  "data-entry-placeholder-color-default": {"value":"#454d56","type":"color","description":"🟣 Token alias: Colore declinato dal secondario che identifica un elemento con cui l’utente può interagire","filePath":"tokens/design-tokens-example.json","isSource":true,"original":{"value":"{color.global.secondary-100.value}","type":"color","description":"🟣 Token alias: Colore declinato dal secondario che identifica un elemento con cui l’utente può interagire"},"name":"interactive-secondary-default","attributes":{},"path":["color","alias","interactive-secondary-default"]},
  "data-entry-placeholder-color-hover": {"value":"#005980","type":"color","description":"🟣 Token alias: Colore declinato dal primario che identifica il passaggio del mouse su un elemento","filePath":"tokens/design-tokens-example.json","isSource":true,"original":{"value":"{color.global.dark-primary-110.value}","type":"color","description":"🟣 Token alias: Colore declinato dal primario che identifica il passaggio del mouse su un elemento"},"name":"interactive-primary-hover","attributes":{},"path":["color","alias","interactive-primary-hover"]},
  "data-entry-placeholder-color-focus": {"value":"#004766","type":"color","description":"🟣 Token alias: Colore declinato dal primario che identifica la selezione di un elemento usando una tastiera o una voce","filePath":"tokens/design-tokens-example.json","isSource":true,"original":{"value":"{color.global.dark-primary-115.value}","type":"color","description":"🟣 Token alias: Colore declinato dal primario che identifica la selezione di un elemento usando una tastiera o una voce"},"name":"interactive-primary-focus","attributes":{},"path":["color","alias","interactive-primary-focus"]},
  "data-entry-placeholder-color-valued": {"value":"#454d56","type":"color","description":"🟣 Token alias: Colore declinato dal secondario che identifica un elemento con cui l’utente può interagire","filePath":"tokens/design-tokens-example.json","isSource":true,"original":{"value":"{color.global.secondary-100.value}","type":"color","description":"🟣 Token alias: Colore declinato dal secondario che identifica un elemento con cui l’utente può interagire"},"name":"interactive-secondary-default","attributes":{},"path":["color","alias","interactive-secondary-default"]},
  "data-entry-border-color-default": {"value":"#454d56","type":"color","description":"🟣 Token alias: Colore declinato dal secondario che identifica un elemento con cui l’utente può interagire","filePath":"tokens/design-tokens-example.json","isSource":true,"original":{"value":"{color.global.secondary-100.value}","type":"color","description":"🟣 Token alias: Colore declinato dal secondario che identifica un elemento con cui l’utente può interagire"},"name":"interactive-secondary-default","attributes":{},"path":["color","alias","interactive-secondary-default"]},
  "data-entry-border-color-hover": {"value":"#005980","type":"color","description":"🟣 Token alias: Colore declinato dal primario che identifica il passaggio del mouse su un elemento","filePath":"tokens/design-tokens-example.json","isSource":true,"original":{"value":"{color.global.dark-primary-110.value}","type":"color","description":"🟣 Token alias: Colore declinato dal primario che identifica il passaggio del mouse su un elemento"},"name":"interactive-primary-hover","attributes":{},"path":["color","alias","interactive-primary-hover"]},
  "data-entry-border-color-focus": {"value":"#004766","type":"color","description":"🟣 Token alias: Colore declinato dal primario che identifica la selezione di un elemento usando una tastiera o una voce","filePath":"tokens/design-tokens-example.json","isSource":true,"original":{"value":"{color.global.dark-primary-115.value}","type":"color","description":"🟣 Token alias: Colore declinato dal primario che identifica la selezione di un elemento usando una tastiera o una voce"},"name":"interactive-primary-focus","attributes":{},"path":["color","alias","interactive-primary-focus"]},
  "data-entry-border-color-valued": {"value":"#454d56","type":"color","description":"🟣 Token alias: Colore declinato dal secondario che identifica un elemento con cui l’utente può interagire","filePath":"tokens/design-tokens-example.json","isSource":true,"original":{"value":"{color.global.secondary-100.value}","type":"color","description":"🟣 Token alias: Colore declinato dal secondario che identifica un elemento con cui l’utente può interagire"},"name":"interactive-secondary-default","attributes":{},"path":["color","alias","interactive-secondary-default"]},
  "ColorSpecificDataEntryBorderColorError": {"value":"#aa224f","type":"color","description":"🟡 Token globale: Colore semantico che identifica uno stato di allerta/errore","filePath":"tokens/design-tokens-example.json","isSource":true,"original":{"value":"#aa224f","type":"color","description":"🟡 Token globale: Colore semantico che identifica uno stato di allerta/errore"},"name":"ColorGlobalSemanticAlert100","attributes":{"category":"color","type":"global","item":"semantic-alert-100"},"path":["color","global","semantic-alert-100"]},
  "ColorSpecificDataEntryBorderColorWarning": {"value":"#e26334","type":"color","description":"🟡 Token globale: Colore semantico che identifica uno stato di attenzione","filePath":"tokens/design-tokens-example.json","isSource":true,"original":{"value":"#e26334","type":"color","description":"🟡 Token globale: Colore semantico che identifica uno stato di attenzione"},"name":"ColorGlobalSemanticWarning100","attributes":{"category":"color","type":"global","item":"semantic-warning-100"},"path":["color","global","semantic-warning-100"]},
  "ColorSpecificDataEntryBorderColorSuccess": {"value":"#049894","type":"color","description":"🟡 Token globale: Colore semantico che identifica un stato di successo dell’applicazione","filePath":"tokens/design-tokens-example.json","isSource":true,"original":{"value":"#049894","type":"color","description":"🟡 Token globale: Colore semantico che identifica un stato di successo dell’applicazione"},"name":"ColorGlobalSemanticSuccesso100","attributes":{"category":"color","type":"global","item":"semantic-successo-100"},"path":["color","global","semantic-successo-100"]},
  "option-background-color-hover": {"value":"#005980","type":"color","description":"🟣 Token alias: Colore declinato dal primario che identifica il passaggio del mouse su un elemento","filePath":"tokens/design-tokens-example.json","isSource":true,"original":{"value":"{color.global.dark-primary-110.value}","type":"color","description":"🟣 Token alias: Colore declinato dal primario che identifica il passaggio del mouse su un elemento"},"name":"interactive-primary-hover","attributes":{},"path":["color","alias","interactive-primary-hover"]},
  "option-background-color-focus": {"value":"#004766","type":"color","description":"🟣 Token alias: Colore declinato dal primario che identifica la selezione di un elemento usando una tastiera o una voce","filePath":"tokens/design-tokens-example.json","isSource":true,"original":{"value":"{color.global.dark-primary-115.value}","type":"color","description":"🟣 Token alias: Colore declinato dal primario che identifica la selezione di un elemento usando una tastiera o una voce"},"name":"interactive-primary-focus","attributes":{},"path":["color","alias","interactive-primary-focus"]},
  "option-background-color-pressed": {"value":"#00354c","type":"color","description":"🟣 Token alias: Colore declinato dal primario che identifica un elemento con cui l’utente ha interagito","filePath":"tokens/design-tokens-example.json","isSource":true,"original":{"value":"{color.global.dark-primary-120.value}","type":"color","description":"🟣 Token alias: Colore declinato dal primario che identifica un elemento con cui l’utente ha interagito"},"name":"interactive-primary-pressed","attributes":{},"path":["color","alias","interactive-primary-pressed"]},
  "option-background-color-valued": {"value":"#007db3","type":"color","description":"🟣 Token alias: Colore primario che identifica un elemento con cui l’utente può interagire","filePath":"tokens/design-tokens-example.json","isSource":true,"original":{"value":"{color.global.primary-100.value}","type":"color","description":"🟣 Token alias: Colore primario che identifica un elemento con cui l’utente può interagire"},"name":"interactive-primary-default","attributes":{},"path":["color","alias","interactive-primary-default"]},
  "ColorSpecificProgressbarBackgroundColor": "#000000",
  "TypographyGlobalFontFamily01": "Titillium Web",
  "TypographyGlobalFontFamily02": "Lora",
  "TypographyGlobalFontFamily03": "Roboto Mono",
  "TypographyGlobalLineHeights10": "54",
  "TypographyGlobalLineHeights11": "60",
  "TypographyGlobalLineHeights12": "66",
  "TypographyGlobalLineHeights13": "72",
  "TypographyGlobalLineHeights14": "78",
  "TypographyGlobalLineHeights15": "84",
  "TypographyGlobalLineHeights01": "16",
  "TypographyGlobalLineHeights02": "18",
  "TypographyGlobalLineHeights03": "21",
  "TypographyGlobalLineHeights04": "24",
  "TypographyGlobalLineHeights05": "27",
  "TypographyGlobalLineHeights06": "30",
  "TypographyGlobalLineHeights07": "36",
  "TypographyGlobalLineHeights08": "42",
  "TypographyGlobalLineHeights09": "48",
  "TypographyGlobalFontWeights300": "Light",
  "TypographyGlobalFontWeights400": "Regular",
  "TypographyGlobalFontWeights500": "Medium",
  "TypographyGlobalFontWeights600": "SemiBold",
  "TypographyGlobalFontWeights700": "Bold",
  "TypographyGlobalFontWeights700I": "Bold Italic",
  "TypographyGlobalFontWeights600I": "SemiBold Italic",
  "TypographyGlobalFontWeights500I": "Medium Italic",
  "TypographyGlobalFontWeights400I": "Italic",
  "TypographyGlobalFontWeights300I": "Light Italic",
  "TypographyGlobalFontSize10": "36",
  "TypographyGlobalFontSize11": "40",
  "TypographyGlobalFontSize12": "44",
  "TypographyGlobalFontSize13": "48",
  "TypographyGlobalFontSize14": "52",
  "TypographyGlobalFontSize15": "56",
  "TypographyGlobalFontSize01": "10",
  "TypographyGlobalFontSize02": "12",
  "TypographyGlobalFontSize03": "14",
  "TypographyGlobalFontSize04": "16",
  "TypographyGlobalFontSize05": "18",
  "TypographyGlobalFontSize06": "20",
  "TypographyGlobalFontSize07": "24",
  "TypographyGlobalFontSize08": "28",
  "TypographyGlobalFontSize09": "32",
  "TypographyAliasFontFamilyHeading01": {"value":"Titillium Web","type":"fontFamilies","description":"🟡 Token globale: Font istituzionale INPS, usato per quasi la totalità dei testi","filePath":"tokens/design-tokens-example.json","isSource":true,"original":{"value":"Titillium Web","type":"fontFamilies","description":"🟡 Token globale: Font istituzionale INPS, usato per quasi la totalità dei testi"},"name":"TypographyGlobalFontFamily01","attributes":{"category":"typography","type":"global","item":"fontFamily","subitem":"01"},"path":["typography","global","fontFamily","01"]},
  "TypographyAliasFontFamilyText01": {"value":"Titillium Web","type":"fontFamilies","description":"🟡 Token globale: Font istituzionale INPS, usato per quasi la totalità dei testi","filePath":"tokens/design-tokens-example.json","isSource":true,"original":{"value":"Titillium Web","type":"fontFamilies","description":"🟡 Token globale: Font istituzionale INPS, usato per quasi la totalità dei testi"},"name":"TypographyGlobalFontFamily01","attributes":{"category":"typography","type":"global","item":"fontFamily","subitem":"01"},"path":["typography","global","fontFamily","01"]},
  "TypographyAliasFontFamilyText02": {"value":"Lora","type":"fontFamilies","description":"🟡 Token globale: Font da abbinare al Titillium Web, usato per lettura immersiva (testi lunghi)","filePath":"tokens/design-tokens-example.json","isSource":true,"original":{"value":"Lora","type":"fontFamilies","description":"🟡 Token globale: Font da abbinare al Titillium Web, usato per lettura immersiva (testi lunghi)"},"name":"TypographyGlobalFontFamily02","attributes":{"category":"typography","type":"global","item":"fontFamily","subitem":"02"},"path":["typography","global","fontFamily","02"]},
  "TypographyAliasFontFamilyNumber03": {"value":"Roboto Mono","type":"fontFamilies","description":"🟡 Token globale: Font usato per valori numerici","filePath":"tokens/design-tokens-example.json","isSource":true,"original":{"value":"Roboto Mono","type":"fontFamilies","description":"🟡 Token globale: Font usato per valori numerici"},"name":"TypographyGlobalFontFamily03","attributes":{"category":"typography","type":"global","item":"fontFamily","subitem":"03"},"path":["typography","global","fontFamily","03"]},
  "TypographyAliasH1XlSize15": {"value":"56","type":"fontSizes","description":"🟡 Token globale: Token di tipografia costante per la dimensione del carattere","filePath":"tokens/design-tokens-example.json","isSource":true,"original":{"value":"56","type":"fontSizes","description":"🟡 Token globale: Token di tipografia costante per la dimensione del carattere"},"name":"TypographyGlobalFontSize15","attributes":{"category":"typography","type":"global","item":"fontSize","subitem":"15"},"path":["typography","global","fontSize","15"]},
  "TypographyAliasH1LgSize14": {"value":"52","type":"fontSizes","description":"🟡 Token globale: Token di tipografia costante per la dimensione del carattere","filePath":"tokens/design-tokens-example.json","isSource":true,"original":{"value":"52","type":"fontSizes","description":"🟡 Token globale: Token di tipografia costante per la dimensione del carattere"},"name":"TypographyGlobalFontSize14","attributes":{"category":"typography","type":"global","item":"fontSize","subitem":"14"},"path":["typography","global","fontSize","14"]},
  "TypographyAliasH1MdSize13": {"value":"48","type":"fontSizes","description":"🟡 Token globale: Token di tipografia costante per la dimensione del carattere","filePath":"tokens/design-tokens-example.json","isSource":true,"original":{"value":"48","type":"fontSizes","description":"🟡 Token globale: Token di tipografia costante per la dimensione del carattere"},"name":"TypographyGlobalFontSize13","attributes":{"category":"typography","type":"global","item":"fontSize","subitem":"13"},"path":["typography","global","fontSize","13"]},
  "TypographyAliasH2LgSize12": {"value":"44","type":"fontSizes","description":"🟡 Token globale: Token di tipografia costante per la dimensione del carattere","filePath":"tokens/design-tokens-example.json","isSource":true,"original":{"value":"44","type":"fontSizes","description":"🟡 Token globale: Token di tipografia costante per la dimensione del carattere"},"name":"TypographyGlobalFontSize12","attributes":{"category":"typography","type":"global","item":"fontSize","subitem":"12"},"path":["typography","global","fontSize","12"]},
  "TypographyAliasH2MdSize11": {"value":"40","type":"fontSizes","description":"🟡 Token globale: Token di tipografia costante per la dimensione del carattere","filePath":"tokens/design-tokens-example.json","isSource":true,"original":{"value":"40","type":"fontSizes","description":"🟡 Token globale: Token di tipografia costante per la dimensione del carattere"},"name":"TypographyGlobalFontSize11","attributes":{"category":"typography","type":"global","item":"fontSize","subitem":"11"},"path":["typography","global","fontSize","11"]},
  "TypographyAliasH3LgSize10": {"value":"36","type":"fontSizes","description":"🟡 Token globale: Token di tipografia costante per la dimensione del carattere","filePath":"tokens/design-tokens-example.json","isSource":true,"original":{"value":"36","type":"fontSizes","description":"🟡 Token globale: Token di tipografia costante per la dimensione del carattere"},"name":"TypographyGlobalFontSize10","attributes":{"category":"typography","type":"global","item":"fontSize","subitem":"10"},"path":["typography","global","fontSize","10"]},
  "TypographyAliasH3MdSize09": {"value":"32","type":"fontSizes","description":"🟡 Token globale: Token di tipografia costante per la dimensione del carattere","filePath":"tokens/design-tokens-example.json","isSource":true,"original":{"value":"32","type":"fontSizes","description":"🟡 Token globale: Token di tipografia costante per la dimensione del carattere"},"name":"TypographyGlobalFontSize09","attributes":{"category":"typography","type":"global","item":"fontSize","subitem":"09"},"path":["typography","global","fontSize","09"]},
  "TypographyAliasH4LgSize08": {"value":"28","type":"fontSizes","description":"🟡 Token globale: Token di tipografia costante per la dimensione del carattere","filePath":"tokens/design-tokens-example.json","isSource":true,"original":{"value":"28","type":"fontSizes","description":"🟡 Token globale: Token di tipografia costante per la dimensione del carattere"},"name":"TypographyGlobalFontSize08","attributes":{"category":"typography","type":"global","item":"fontSize","subitem":"08"},"path":["typography","global","fontSize","08"]},
  "TypographyAliasH4MdSize07": {"value":"24","type":"fontSizes","description":"🟡 Token globale: Token di tipografia costante per la dimensione del carattere","filePath":"tokens/design-tokens-example.json","isSource":true,"original":{"value":"24","type":"fontSizes","description":"🟡 Token globale: Token di tipografia costante per la dimensione del carattere"},"name":"TypographyGlobalFontSize07","attributes":{"category":"typography","type":"global","item":"fontSize","subitem":"07"},"path":["typography","global","fontSize","07"]},
  "TypographyAliasH5MdSize06": {"value":"20","type":"fontSizes","description":"🟡 Token globale: Token di tipografia costante per la dimensione del carattere","filePath":"tokens/design-tokens-example.json","isSource":true,"original":{"value":"20","type":"fontSizes","description":"🟡 Token globale: Token di tipografia costante per la dimensione del carattere"},"name":"TypographyGlobalFontSize06","attributes":{"category":"typography","type":"global","item":"fontSize","subitem":"06"},"path":["typography","global","fontSize","06"]},
  "TypographyAliasH6MdSize05": {"value":"18","type":"fontSizes","description":"🟡 Token globale: Token di tipografia costante per la dimensione del carattere","filePath":"tokens/design-tokens-example.json","isSource":true,"original":{"value":"18","type":"fontSizes","description":"🟡 Token globale: Token di tipografia costante per la dimensione del carattere"},"name":"TypographyGlobalFontSize05","attributes":{"category":"typography","type":"global","item":"fontSize","subitem":"05"},"path":["typography","global","fontSize","05"]},
  "TypographyAliasPLgSize05": {"value":"18","type":"fontSizes","description":"🟡 Token globale: Token di tipografia costante per la dimensione del carattere","filePath":"tokens/design-tokens-example.json","isSource":true,"original":{"value":"18","type":"fontSizes","description":"🟡 Token globale: Token di tipografia costante per la dimensione del carattere"},"name":"TypographyGlobalFontSize05","attributes":{"category":"typography","type":"global","item":"fontSize","subitem":"05"},"path":["typography","global","fontSize","05"]},
  "TypographyAliasPMdSize04": {"value":"16","type":"fontSizes","description":"🟡 Token globale: Token di tipografia costante per la dimensione del carattere","filePath":"tokens/design-tokens-example.json","isSource":true,"original":{"value":"16","type":"fontSizes","description":"🟡 Token globale: Token di tipografia costante per la dimensione del carattere"},"name":"TypographyGlobalFontSize04","attributes":{"category":"typography","type":"global","item":"fontSize","subitem":"04"},"path":["typography","global","fontSize","04"]},
  "TypographyAliasLabelMdSize04": {"value":"16","type":"fontSizes","description":"🟡 Token globale: Token di tipografia costante per la dimensione del carattere","filePath":"tokens/design-tokens-example.json","isSource":true,"original":{"value":"16","type":"fontSizes","description":"🟡 Token globale: Token di tipografia costante per la dimensione del carattere"},"name":"TypographyGlobalFontSize04","attributes":{"category":"typography","type":"global","item":"fontSize","subitem":"04"},"path":["typography","global","fontSize","04"]},
  "TypographyAliasDisclaimerMdSize03": {"value":"14","type":"fontSizes","description":"🟡 Token globale: Token di tipografia costante per la dimensione del carattere","filePath":"tokens/design-tokens-example.json","isSource":true,"original":{"value":"14","type":"fontSizes","description":"🟡 Token globale: Token di tipografia costante per la dimensione del carattere"},"name":"TypographyGlobalFontSize03","attributes":{"category":"typography","type":"global","item":"fontSize","subitem":"03"},"path":["typography","global","fontSize","03"]},
  "TypographyAliasLinkLgSize05": {"value":"18","type":"fontSizes","description":"🟡 Token globale: Token di tipografia costante per la dimensione del carattere","filePath":"tokens/design-tokens-example.json","isSource":true,"original":{"value":"18","type":"fontSizes","description":"🟡 Token globale: Token di tipografia costante per la dimensione del carattere"},"name":"TypographyGlobalFontSize05","attributes":{"category":"typography","type":"global","item":"fontSize","subitem":"05"},"path":["typography","global","fontSize","05"]},
  "TypographyAliasLinkMdSize04": {"value":"16","type":"fontSizes","description":"🟡 Token globale: Token di tipografia costante per la dimensione del carattere","filePath":"tokens/design-tokens-example.json","isSource":true,"original":{"value":"16","type":"fontSizes","description":"🟡 Token globale: Token di tipografia costante per la dimensione del carattere"},"name":"TypographyGlobalFontSize04","attributes":{"category":"typography","type":"global","item":"fontSize","subitem":"04"},"path":["typography","global","fontSize","04"]},
  "TypographyAliasH1XlLineHeight15": {"value":"84","type":"lineHeights","description":" Token globale: Token di tipografia costante per l’interlinea del carattere (da associare al font-size-15 corrispondente) ","filePath":"tokens/design-tokens-example.json","isSource":true,"original":{"value":"84","type":"lineHeights","description":" Token globale: Token di tipografia costante per l’interlinea del carattere (da associare al font-size-15 corrispondente) "},"name":"TypographyGlobalLineHeights15","attributes":{"category":"typography","type":"global","item":"lineHeights","subitem":"15"},"path":["typography","global","lineHeights","15"]},
  "TypographyAliasH1LgLineHeight14": {"value":"78","type":"lineHeights","description":"🟡 Token globale: Token di tipografia costante per l’interlinea del carattere (da associare al font-size-14 corrispondente) ","filePath":"tokens/design-tokens-example.json","isSource":true,"original":{"value":"78","type":"lineHeights","description":"🟡 Token globale: Token di tipografia costante per l’interlinea del carattere (da associare al font-size-14 corrispondente) "},"name":"TypographyGlobalLineHeights14","attributes":{"category":"typography","type":"global","item":"lineHeights","subitem":"14"},"path":["typography","global","lineHeights","14"]},
  "TypographyAliasH1MdLineHeight13": {"value":"72","type":"lineHeights","description":"🟡 Token globale: Token di tipografia costante per l’interlinea del carattere (da associare al font-size-13 corrispondente) ","filePath":"tokens/design-tokens-example.json","isSource":true,"original":{"value":"72","type":"lineHeights","description":"🟡 Token globale: Token di tipografia costante per l’interlinea del carattere (da associare al font-size-13 corrispondente) "},"name":"TypographyGlobalLineHeights13","attributes":{"category":"typography","type":"global","item":"lineHeights","subitem":"13"},"path":["typography","global","lineHeights","13"]},
  "TypographyAliasH2LgLineHeight12": {"value":"66","type":"lineHeights","description":"🟡 Token globale: Token di tipografia costante per l’interlinea del carattere (da associare al font-size-12 corrispondente) ","filePath":"tokens/design-tokens-example.json","isSource":true,"original":{"value":"66","type":"lineHeights","description":"🟡 Token globale: Token di tipografia costante per l’interlinea del carattere (da associare al font-size-12 corrispondente) "},"name":"TypographyGlobalLineHeights12","attributes":{"category":"typography","type":"global","item":"lineHeights","subitem":"12"},"path":["typography","global","lineHeights","12"]},
  "TypographyAliasH2MdLineHeight11": {"value":"60","type":"lineHeights","description":"🟡 Token globale: Token di tipografia costante per l’interlinea del carattere (da associare al font-size-11 corrispondente) ","filePath":"tokens/design-tokens-example.json","isSource":true,"original":{"value":"60","type":"lineHeights","description":"🟡 Token globale: Token di tipografia costante per l’interlinea del carattere (da associare al font-size-11 corrispondente) "},"name":"TypographyGlobalLineHeights11","attributes":{"category":"typography","type":"global","item":"lineHeights","subitem":"11"},"path":["typography","global","lineHeights","11"]},
  "TypographyAliasH3LgLineHeight10": {"value":"54","type":"lineHeights","description":"🟡 Token globale: Token di tipografia costante per l’interlinea del carattere (da associare al font-size-10 corrispondente) ","filePath":"tokens/design-tokens-example.json","isSource":true,"original":{"value":"54","type":"lineHeights","description":"🟡 Token globale: Token di tipografia costante per l’interlinea del carattere (da associare al font-size-10 corrispondente) "},"name":"TypographyGlobalLineHeights10","attributes":{"category":"typography","type":"global","item":"lineHeights","subitem":"10"},"path":["typography","global","lineHeights","10"]},
  "TypographyAliasH3MdLineHeight09": {"value":"48","type":"lineHeights","description":"🟡 Token globale: Token di tipografia costante per l’interlinea del carattere (da associare al font-size-09 corrispondente) ","filePath":"tokens/design-tokens-example.json","isSource":true,"original":{"value":"48","type":"lineHeights","description":"🟡 Token globale: Token di tipografia costante per l’interlinea del carattere (da associare al font-size-09 corrispondente) "},"name":"TypographyGlobalLineHeights09","attributes":{"category":"typography","type":"global","item":"lineHeights","subitem":"09"},"path":["typography","global","lineHeights","09"]},
  "TypographyAliasH4LgLineHeight08": {"value":"42","type":"lineHeights","description":"🟡 Token globale: Token di tipografia costante per l’interlinea del carattere (da associare al font-size-08 corrispondente) ","filePath":"tokens/design-tokens-example.json","isSource":true,"original":{"value":"42","type":"lineHeights","description":"🟡 Token globale: Token di tipografia costante per l’interlinea del carattere (da associare al font-size-08 corrispondente) "},"name":"TypographyGlobalLineHeights08","attributes":{"category":"typography","type":"global","item":"lineHeights","subitem":"08"},"path":["typography","global","lineHeights","08"]},
  "TypographyAliasH4MdLineHeight07": {"value":"36","type":"lineHeights","description":"🟡 Token globale: Token di tipografia costante per l’interlinea del carattere (da associare al font-size-07 corrispondente) ","filePath":"tokens/design-tokens-example.json","isSource":true,"original":{"value":"36","type":"lineHeights","description":"🟡 Token globale: Token di tipografia costante per l’interlinea del carattere (da associare al font-size-07 corrispondente) "},"name":"TypographyGlobalLineHeights07","attributes":{"category":"typography","type":"global","item":"lineHeights","subitem":"07"},"path":["typography","global","lineHeights","07"]},
  "TypographyAliasH5MdLineHeight06": {"value":"30","type":"lineHeights","description":"🟡 Token globale: Token di tipografia costante per l’interlinea del carattere (da associare al font-size-06 corrispondente) ","filePath":"tokens/design-tokens-example.json","isSource":true,"original":{"value":"30","type":"lineHeights","description":"🟡 Token globale: Token di tipografia costante per l’interlinea del carattere (da associare al font-size-06 corrispondente) "},"name":"TypographyGlobalLineHeights06","attributes":{"category":"typography","type":"global","item":"lineHeights","subitem":"06"},"path":["typography","global","lineHeights","06"]},
  "TypographyAliasH6MdLineHeight05": {"value":"27","type":"lineHeights","description":"🟡 Token globale: Token di tipografia costante per l’interlinea del carattere (da associare al font-size-05 corrispondente) ","filePath":"tokens/design-tokens-example.json","isSource":true,"original":{"value":"27","type":"lineHeights","description":"🟡 Token globale: Token di tipografia costante per l’interlinea del carattere (da associare al font-size-05 corrispondente) "},"name":"TypographyGlobalLineHeights05","attributes":{"category":"typography","type":"global","item":"lineHeights","subitem":"05"},"path":["typography","global","lineHeights","05"]},
  "TypographyAliasPLgLineHeight05": {"value":"27","type":"lineHeights","description":"🟡 Token globale: Token di tipografia costante per l’interlinea del carattere (da associare al font-size-05 corrispondente) ","filePath":"tokens/design-tokens-example.json","isSource":true,"original":{"value":"27","type":"lineHeights","description":"🟡 Token globale: Token di tipografia costante per l’interlinea del carattere (da associare al font-size-05 corrispondente) "},"name":"TypographyGlobalLineHeights05","attributes":{"category":"typography","type":"global","item":"lineHeights","subitem":"05"},"path":["typography","global","lineHeights","05"]},
  "TypographyAliasPMdLineHeight04": {"value":"24","type":"lineHeights","description":"🟡 Token globale: Token di tipografia costante per l’interlinea del carattere (da associare al font-size-04 corrispondente) ","filePath":"tokens/design-tokens-example.json","isSource":true,"original":{"value":"24","type":"lineHeights","description":"🟡 Token globale: Token di tipografia costante per l’interlinea del carattere (da associare al font-size-04 corrispondente) "},"name":"TypographyGlobalLineHeights04","attributes":{"category":"typography","type":"global","item":"lineHeights","subitem":"04"},"path":["typography","global","lineHeights","04"]},
  "TypographyAliasLabelMdLineHeight04": {"value":"24","type":"lineHeights","description":"🟡 Token globale: Token di tipografia costante per l’interlinea del carattere (da associare al font-size-04 corrispondente) ","filePath":"tokens/design-tokens-example.json","isSource":true,"original":{"value":"24","type":"lineHeights","description":"🟡 Token globale: Token di tipografia costante per l’interlinea del carattere (da associare al font-size-04 corrispondente) "},"name":"TypographyGlobalLineHeights04","attributes":{"category":"typography","type":"global","item":"lineHeights","subitem":"04"},"path":["typography","global","lineHeights","04"]},
  "TypographyAliasDisclaimerMdLineHeight03": {"value":"21","type":"lineHeights","description":"🟡 Token globale: Token di tipografia costante per l’interlinea del carattere (da associare al font-size-03 corrispondente) ","filePath":"tokens/design-tokens-example.json","isSource":true,"original":{"value":"21","type":"lineHeights","description":"🟡 Token globale: Token di tipografia costante per l’interlinea del carattere (da associare al font-size-03 corrispondente) "},"name":"TypographyGlobalLineHeights03","attributes":{"category":"typography","type":"global","item":"lineHeights","subitem":"03"},"path":["typography","global","lineHeights","03"]},
  "TypographyAliasLinkLgLineHeight05": {"value":"27","type":"lineHeights","description":"🟡 Token globale: Token di tipografia costante per l’interlinea del carattere (da associare al font-size-05 corrispondente) ","filePath":"tokens/design-tokens-example.json","isSource":true,"original":{"value":"27","type":"lineHeights","description":"🟡 Token globale: Token di tipografia costante per l’interlinea del carattere (da associare al font-size-05 corrispondente) "},"name":"TypographyGlobalLineHeights05","attributes":{"category":"typography","type":"global","item":"lineHeights","subitem":"05"},"path":["typography","global","lineHeights","05"]},
  "TypographyAliasLinkMdLineHeight04": {"value":"24","type":"lineHeights","description":"🟡 Token globale: Token di tipografia costante per l’interlinea del carattere (da associare al font-size-04 corrispondente) ","filePath":"tokens/design-tokens-example.json","isSource":true,"original":{"value":"24","type":"lineHeights","description":"🟡 Token globale: Token di tipografia costante per l’interlinea del carattere (da associare al font-size-04 corrispondente) "},"name":"TypographyGlobalLineHeights04","attributes":{"category":"typography","type":"global","item":"lineHeights","subitem":"04"},"path":["typography","global","lineHeights","04"]},
  "TypographyAliasH1FontWeight700": {"value":"Bold","type":"fontWeights","description":"🟡 Token globale: Font bold, usato per enfatizzare contenuti specifici (esempio: titoli pagina)","filePath":"tokens/design-tokens-example.json","isSource":true,"original":{"value":"Bold","type":"fontWeights","description":"🟡 Token globale: Font bold, usato per enfatizzare contenuti specifici (esempio: titoli pagina)"},"name":"TypographyGlobalFontWeights700","attributes":{"category":"typography","type":"global","item":"fontWeights","subitem":"700"},"path":["typography","global","fontWeights","700"]},
  "TypographyAliasH2FontWeight700": {"value":"Bold","type":"fontWeights","description":"🟡 Token globale: Font bold, usato per enfatizzare contenuti specifici (esempio: titoli pagina)","filePath":"tokens/design-tokens-example.json","isSource":true,"original":{"value":"Bold","type":"fontWeights","description":"🟡 Token globale: Font bold, usato per enfatizzare contenuti specifici (esempio: titoli pagina)"},"name":"TypographyGlobalFontWeights700","attributes":{"category":"typography","type":"global","item":"fontWeights","subitem":"700"},"path":["typography","global","fontWeights","700"]},
  "TypographyAliasH3FontWeight700": {"value":"Bold","type":"fontWeights","description":"🟡 Token globale: Font bold, usato per enfatizzare contenuti specifici (esempio: titoli pagina)","filePath":"tokens/design-tokens-example.json","isSource":true,"original":{"value":"Bold","type":"fontWeights","description":"🟡 Token globale: Font bold, usato per enfatizzare contenuti specifici (esempio: titoli pagina)"},"name":"TypographyGlobalFontWeights700","attributes":{"category":"typography","type":"global","item":"fontWeights","subitem":"700"},"path":["typography","global","fontWeights","700"]},
  "TypographyAliasH4FontWeight700": {"value":"Bold","type":"fontWeights","description":"🟡 Token globale: Font bold, usato per enfatizzare contenuti specifici (esempio: titoli pagina)","filePath":"tokens/design-tokens-example.json","isSource":true,"original":{"value":"Bold","type":"fontWeights","description":"🟡 Token globale: Font bold, usato per enfatizzare contenuti specifici (esempio: titoli pagina)"},"name":"TypographyGlobalFontWeights700","attributes":{"category":"typography","type":"global","item":"fontWeights","subitem":"700"},"path":["typography","global","fontWeights","700"]},
  "TypographyAliasH5FontWeight600": {"value":"SemiBold","type":"fontWeights","description":"🟡 Token globale: Font semibold, usato per enfatizzare contenuti specifici (esempio: label form)","filePath":"tokens/design-tokens-example.json","isSource":true,"original":{"value":"SemiBold","type":"fontWeights","description":"🟡 Token globale: Font semibold, usato per enfatizzare contenuti specifici (esempio: label form)"},"name":"TypographyGlobalFontWeights600","attributes":{"category":"typography","type":"global","item":"fontWeights","subitem":"600"},"path":["typography","global","fontWeights","600"]},
  "TypographyAliasH6FontWeight400": {"value":"Regular","type":"fontWeights","description":"🟡 Token globale: Font regular, usato tutti i testi come paragrafi e placeholder all’interno dei text-field","filePath":"tokens/design-tokens-example.json","isSource":true,"original":{"value":"Regular","type":"fontWeights","description":"🟡 Token globale: Font regular, usato tutti i testi come paragrafi e placeholder all’interno dei text-field"},"name":"TypographyGlobalFontWeights400","attributes":{"category":"typography","type":"global","item":"fontWeights","subitem":"400"},"path":["typography","global","fontWeights","400"]},
  "TypographyAliasPFontWeight400": {"value":"Regular","type":"fontWeights","description":"🟡 Token globale: Font regular, usato tutti i testi come paragrafi e placeholder all’interno dei text-field","filePath":"tokens/design-tokens-example.json","isSource":true,"original":{"value":"Regular","type":"fontWeights","description":"🟡 Token globale: Font regular, usato tutti i testi come paragrafi e placeholder all’interno dei text-field"},"name":"TypographyGlobalFontWeights400","attributes":{"category":"typography","type":"global","item":"fontWeights","subitem":"400"},"path":["typography","global","fontWeights","400"]},
  "TypographyAliasLabelFontWeight600": {"value":"SemiBold","type":"fontWeights","description":"🟡 Token globale: Font semibold, usato per enfatizzare contenuti specifici (esempio: label form)","filePath":"tokens/design-tokens-example.json","isSource":true,"original":{"value":"SemiBold","type":"fontWeights","description":"🟡 Token globale: Font semibold, usato per enfatizzare contenuti specifici (esempio: label form)"},"name":"TypographyGlobalFontWeights600","attributes":{"category":"typography","type":"global","item":"fontWeights","subitem":"600"},"path":["typography","global","fontWeights","600"]},
  "TypographyAliasDisclaimerFontWeight400": {"value":"Regular","type":"fontWeights","description":"🟡 Token globale: Font regular, usato tutti i testi come paragrafi e placeholder all’interno dei text-field","filePath":"tokens/design-tokens-example.json","isSource":true,"original":{"value":"Regular","type":"fontWeights","description":"🟡 Token globale: Font regular, usato tutti i testi come paragrafi e placeholder all’interno dei text-field"},"name":"TypographyGlobalFontWeights400","attributes":{"category":"typography","type":"global","item":"fontWeights","subitem":"400"},"path":["typography","global","fontWeights","400"]},
  "TypographyAliasLinkFontWeight700": {"value":"Bold","type":"fontWeights","description":"🟡 Token globale: Font bold, usato per enfatizzare contenuti specifici (esempio: titoli pagina)","filePath":"tokens/design-tokens-example.json","isSource":true,"original":{"value":"Bold","type":"fontWeights","description":"🟡 Token globale: Font bold, usato per enfatizzare contenuti specifici (esempio: titoli pagina)"},"name":"TypographyGlobalFontWeights700","attributes":{"category":"typography","type":"global","item":"fontWeights","subitem":"700"},"path":["typography","global","fontWeights","700"]},
  "TypographyStyleH6Medium": {"fontFamily":"$fontFamilies.titillium-web","fontWeight":"$fontWeights.titillium-web-0","lineHeight":"$lineHeights.0","fontSize":"$fontSize.2","letterSpacing":"$letterSpacing.0","paragraphSpacing":"$paragraphSpacing.0","textCase":"$textCase.none","textDecoration":"$textDecoration.none"},
  "TypographyStyleH5Medium": {"fontFamily":"$fontFamilies.titillium-web","fontWeight":"$fontWeights.titillium-web-1","lineHeight":"$lineHeights.1","fontSize":"$fontSize.3","letterSpacing":"$letterSpacing.0","paragraphSpacing":"$paragraphSpacing.0","textCase":"$textCase.none","textDecoration":"$textDecoration.none"},
  "TypographyStyleH4Medium": {"fontFamily":"$fontFamilies.titillium-web","fontWeight":"$fontWeights.titillium-web-2","lineHeight":"$lineHeights.2","fontSize":"$fontSize.4","letterSpacing":"$letterSpacing.0","paragraphSpacing":"$paragraphSpacing.0","textCase":"$textCase.none","textDecoration":"$textDecoration.none"},
  "TypographyStyleH4Large": {"fontFamily":"$fontFamilies.titillium-web","fontWeight":"$fontWeights.titillium-web-2","lineHeight":"$lineHeights.3","fontSize":"$fontSize.5","letterSpacing":"$letterSpacing.0","paragraphSpacing":"$paragraphSpacing.0","textCase":"$textCase.none","textDecoration":"$textDecoration.none"},
  "TypographyStyleH3Medium": {"fontFamily":"$fontFamilies.titillium-web","fontWeight":"$fontWeights.titillium-web-2","lineHeight":"$lineHeights.4","fontSize":"$fontSize.6","letterSpacing":"$letterSpacing.0","paragraphSpacing":"$paragraphSpacing.0","textCase":"$textCase.none","textDecoration":"$textDecoration.none"},
  "TypographyStyleH3Large": {"fontFamily":"$fontFamilies.titillium-web","fontWeight":"$fontWeights.titillium-web-2","lineHeight":"$lineHeights.5","fontSize":"$fontSize.7","letterSpacing":"$letterSpacing.0","paragraphSpacing":"$paragraphSpacing.0","textCase":"$textCase.none","textDecoration":"$textDecoration.none"},
  "TypographyStyleH2Medium": {"fontFamily":"$fontFamilies.titillium-web","fontWeight":"$fontWeights.titillium-web-2","lineHeight":"$lineHeights.6","fontSize":"$fontSize.8","letterSpacing":"$letterSpacing.0","paragraphSpacing":"$paragraphSpacing.0","textCase":"$textCase.none","textDecoration":"$textDecoration.none"},
  "TypographyStyleH2Large": {"fontFamily":"$fontFamilies.titillium-web","fontWeight":"$fontWeights.titillium-web-2","lineHeight":"$lineHeights.7","fontSize":"$fontSize.9","letterSpacing":"$letterSpacing.0","paragraphSpacing":"$paragraphSpacing.0","textCase":"$textCase.none","textDecoration":"$textDecoration.none"},
  "TypographyStyleH1Medium": {"fontFamily":"$fontFamilies.titillium-web","fontWeight":"$fontWeights.titillium-web-2","lineHeight":"$lineHeights.8","fontSize":"$fontSize.10","letterSpacing":"$letterSpacing.0","paragraphSpacing":"$paragraphSpacing.0","textCase":"$textCase.none","textDecoration":"$textDecoration.none"},
  "TypographyStyleH1Large": {"fontFamily":"$fontFamilies.titillium-web","fontWeight":"$fontWeights.titillium-web-2","lineHeight":"$lineHeights.9","fontSize":"$fontSize.11","letterSpacing":"$letterSpacing.0","paragraphSpacing":"$paragraphSpacing.0","textCase":"$textCase.none","textDecoration":"$textDecoration.none"},
  "TypographyStyleH1Extralarge": {"fontFamily":"$fontFamilies.titillium-web","fontWeight":"$fontWeights.titillium-web-2","lineHeight":"$lineHeights.10","fontSize":"$fontSize.12","letterSpacing":"$letterSpacing.0","paragraphSpacing":"$paragraphSpacing.0","textCase":"$textCase.none","textDecoration":"$textDecoration.none"},
  "TypographyStyleLinkPMedium02": {"fontFamily":"$fontFamilies.lora","fontWeight":"$fontWeights.lora-3","lineHeight":"$lineHeights.11","fontSize":"$fontSize.1","letterSpacing":"$letterSpacing.0","paragraphSpacing":"$paragraphSpacing.0","textCase":"$textCase.none","textDecoration":"$textDecoration.underline"},
  "TypographyStyleLinkPMedium01": {"fontFamily":"$fontFamilies.titillium-web","fontWeight":"$fontWeights.titillium-web-2","lineHeight":"$lineHeights.11","fontSize":"$fontSize.1","letterSpacing":"$letterSpacing.0","paragraphSpacing":"$paragraphSpacing.0","textCase":"$textCase.none","textDecoration":"$textDecoration.underline"},
  "TypographyStyleLinkPLarge02": {"fontFamily":"$fontFamilies.lora","fontWeight":"$fontWeights.lora-3","lineHeight":"$lineHeights.0","fontSize":"$fontSize.2","letterSpacing":"$letterSpacing.0","paragraphSpacing":"$paragraphSpacing.0","textCase":"$textCase.none","textDecoration":"$textDecoration.underline"},
  "TypographyStyleLinkPLarge01": {"fontFamily":"$fontFamilies.titillium-web","fontWeight":"$fontWeights.titillium-web-2","lineHeight":"$lineHeights.0","fontSize":"$fontSize.2","letterSpacing":"$letterSpacing.0","paragraphSpacing":"$paragraphSpacing.0","textCase":"$textCase.none","textDecoration":"$textDecoration.underline"},
  "TypographyStyleLabelMedium": {"fontFamily":"$fontFamilies.titillium-web","fontWeight":"$fontWeights.titillium-web-1","lineHeight":"$lineHeights.12","fontSize":"$fontSize.1","letterSpacing":"$letterSpacing.0","paragraphSpacing":"$paragraphSpacing.0","textCase":"$textCase.none","textDecoration":"$textDecoration.none"},
  "TypographyStylePlaceholderBase": {"fontFamily":"$fontFamilies.titillium-web","fontWeight":"$fontWeights.titillium-web-0","lineHeight":"$lineHeights.12","fontSize":"$fontSize.1","letterSpacing":"$letterSpacing.0","paragraphSpacing":"$paragraphSpacing.0","textCase":"$textCase.none","textDecoration":"$textDecoration.none"},
  "TypographyStyleDisclaimerBase": {"fontFamily":"$fontFamilies.titillium-web","fontWeight":"$fontWeights.titillium-web-0","lineHeight":"$lineHeights.13","fontSize":"$fontSize.0","letterSpacing":"$letterSpacing.0","paragraphSpacing":"$paragraphSpacing.0","textCase":"$textCase.none","textDecoration":"$textDecoration.none"},
  "TypographyStylePMedium01": {"fontFamily":"$fontFamilies.titillium-web","fontWeight":"$fontWeights.titillium-web-0","lineHeight":"$lineHeights.11","fontSize":"$fontSize.1","letterSpacing":"$letterSpacing.0","paragraphSpacing":"$paragraphSpacing.0","textCase":"$textCase.none","textDecoration":"$textDecoration.none"},
  "TypographyStylePMedium02": {"fontFamily":"$fontFamilies.lora","fontWeight":"$fontWeights.lora-4","lineHeight":"$lineHeights.11","fontSize":"$fontSize.1","letterSpacing":"$letterSpacing.0","paragraphSpacing":"$paragraphSpacing.0","textCase":"$textCase.none","textDecoration":"$textDecoration.none"},
  "TypographyStylePLarge02": {"fontFamily":"$fontFamilies.lora","fontWeight":"$fontWeights.lora-4","lineHeight":"$lineHeights.0","fontSize":"$fontSize.2","letterSpacing":"$letterSpacing.0","paragraphSpacing":"$paragraphSpacing.0","textCase":"$textCase.none","textDecoration":"$textDecoration.none"},
  "TypographyStylePLarge01": {"fontFamily":"$fontFamilies.titillium-web","fontWeight":"$fontWeights.titillium-web-0","lineHeight":"$lineHeights.0","fontSize":"$fontSize.2","letterSpacing":"$letterSpacing.0","paragraphSpacing":"$paragraphSpacing.0","textCase":"$textCase.none","textDecoration":"$textDecoration.none"},
  "TypographyStyleTextCaseNone": "none",
  "TypographyStyleTextDecorationNone": "none",
  "TypographyStyleTextDecorationUnderline": "underline"
}